pymatrixprofile/__init__.py
pymatrixprofile/pymatrixprofile.py
pymatrixprofile-1.0.0.dist-info/METADATA
pymatrixprofile-1.0.0.dist-info/RECORD
pymatrixprofile-1.0.0.dist-info/WHEEL
pymatrixprofile-1.0.0.dist-info/top_level.txt
tests/__init__.py
tests/test_apis.py
