Metadata-Version: 2.1
Name: pymatrixprofile
Version: 1.0.0
Summary: My Awesome Package.
Home-page: https://github.com/dawran6/cookiecutter-pypackage-minimal
Author: 
Author-email: 
License: UNKNOWN
Platform: UNKNOWN
Classifier: Development Status :: 2 - Pre-Alpha
Classifier: Programming Language :: Python
Classifier: Programming Language :: Python :: 3
Classifier: Programming Language :: Python :: 3.6
Classifier: License :: OSI Approved :: MIT License
